NetBridge/__init__.py
NetBridge-0.0.5.dist-info/License.md
NetBridge-0.0.5.dist-info/METADATA
NetBridge-0.0.5.dist-info/WHEEL
NetBridge-0.0.5.dist-info/top_level.txt
NetBridge-0.0.5.dist-info/RECORD
