Metadata-Version: 2.1
Name: NetBridge
Version: 0.0.5
Summary: Uma biblioteca simples para Comunicação interProgramas e Transferencia de arquivos Locais ou Remotos.
Author: Leonardo Nery
Author-email: leonardonery616@gmail.com
Classifier: Programming Language :: Python :: 3
Classifier: Intended Audience :: Developers
Classifier: License :: OSI Approved :: MIT License
Classifier: Operating System :: OS Independent
Requires-Python: >=3.6
License-File: License.md
